pyht/__init__.py
pyht/async_client.py
pyht/client.py
pyht/inference_coordinates.py
pyht/lease.py
pyht/protos/.keep
pyht/protos/__init__.py
pyht/protos/api_pb2.py
pyht/protos/api_pb2.pyi
pyht/protos/api_pb2_grpc.py
pyht/telemetry.py
pyht/utils.py
pyht-0.1.14.dist-info/LICENSE
pyht-0.1.14.dist-info/METADATA
pyht-0.1.14.dist-info/WHEEL
pyht-0.1.14.dist-info/RECORD
