Metadata-Version: 2.3
Name: pyht
Version: 0.1.14
Summary: 
License: Apache-2.0
Author: Playht Inc.
Author-email: oss@play.ht
Requires-Python: >=3.8,<4.0
Classifier: License :: OSI Approved :: Apache Software License
Classifier: Programming Language :: Python :: 3
Classifier: Programming Language :: Python :: 3.8
Classifier: Programming Language :: Python :: 3.9
Classifier: Programming Language :: Python :: 3.10
Classifier: Programming Language :: Python :: 3.11
Classifier: Programming Language :: Python :: 3.12
Classifier: Programming Language :: Python :: 3.13
Requires-Dist: aiohttp (>=3.10.11,<4.0.0)
Requires-Dist: filelock (>=3.12.4,<4.0.0)
Requires-Dist: grpcio (>=1.70.0,<2.0.0)
Requires-Dist: protobuf (>=5.29.3,<6.0.0)
Requires-Dist: requests (>=2.31.0,<3.0.0)
Requires-Dist: websockets (>=13.1,<14.0)
Project-URL: Homepage, https://github.com/playht/pyht
Project-URL: Repository, https://github.com/playht/pyht
